tldsearcher/__init__.py
tldsearcher/__main__.py
tldsearcher/proxy_requests.py
tldsearcher/tlds.py
tldsearcher/tldsearcher.py
tldsearcher-1.1.0.dist-info/AUTHORS.md
tldsearcher-1.1.0.dist-info/LICENSE
tldsearcher-1.1.0.dist-info/METADATA
tldsearcher-1.1.0.dist-info/WHEEL
tldsearcher-1.1.0.dist-info/top_level.txt
tldsearcher-1.1.0.dist-info/RECORD
