Metadata-Version: 2.1
Name: tldsearcher
Version: 1.1.0
Summary: A tool for finding TLDs for domains
Home-page: https://github.com/plague-anon/tldsearcher
Author: plague
Author-email: plague_anon@protonmail.com
License: GNU General Public License v3
Keywords: tldsearcher
Platform: UNKNOWN
Classifier: Development Status :: 5 - Production/Stable
Classifier: Intended Audience :: Information Technology
Classifier: License :: OSI Approved :: GNU General Public License v3 (GPLv3)
Classifier: Natural Language :: English
Classifier: Operating System :: Unix
Classifier: Topic :: Internet :: WWW/HTTP :: Indexing/Search
Classifier: Programming Language :: Python :: 3
Classifier: Programming Language :: Python :: 3.5
Classifier: Programming Language :: Python :: 3.6
Classifier: Programming Language :: Python :: 3.7
Classifier: Programming Language :: Python :: 3.8
Requires-Python: >=3.5
